auto_parser/__init__.py
auto_parser/test.py
auto_parser-0.0.0.dist-info/METADATA
auto_parser-0.0.0.dist-info/WHEEL
auto_parser-0.0.0.dist-info/entry_points.txt
auto_parser-0.0.0.dist-info/top_level.txt
auto_parser-0.0.0.dist-info/RECORD
